{
  "lotteries": [
    {
      "id": "l01",
      "nome": "Lotofácil",
      "cor": "purple"
    },
    {
      "id": "l02",
      "nome": "Megasena",
      "cor": "green"
    },
    {
      "id": "l03",
      "nome": "Lotomania",
      "cor": "yellow"
    }
  ],
  "admins": [
    {
      "id": "a01",
      "name": "Mauricio",
      "wallet": 500
    },
    {
      "id": "a02",
      "name": "Fran",
      "wallet": 320
    }
  ],
  "sellers": [
    {
      "adminId": "a01",
      "id": "a01s01",
      "name": "Mauricinho",
      "phone": "(21)99999-9999",
      "wallet": 100,
      "comissionType": "percent",
      "comissionValue": 0.15
    },
    {
      "adminId": "u01",
      "id": "a01s02",
      "name": "Mo",
      "phone": "(21)88888-8888",
      "wallet": 150,
      "comissionType": "percent",
      "comissionValue": 0.15
    },
    {
      "adminId": "a01",
      "id": "a02s01",
      "name": "Franzinha",
      "phone": "(21)77777-7777",
      "wallet": 200,
      "comissionType": "percent",
      "comissionValue": 0.1
    },
    {
      "adminId": "a01",
      "id": "a2s02",
      "name": "Franci",
      "phone": "(21)66666-6666",
      "wallet": 325,
      "comissionType": "percent",
      "comissionValue": 0.25
    }
  ],
  "users": [
    {
      "superId": "a01",
      "id": "u01",
      "name": "Roger",
      "wallet": 100,
      "phone": "",
      "pix": ""
    },
    {
      "superId": "a01",
      "id": "u02",
      "name": "Allana",
      "wallet": 200,
      "phone": "",
      "pix": ""
    },
    {
      "superId": "a02",
      "id": "u03",
      "name": "Thais",
      "wallet": 150,
      "phone": "",
      "pix": ""
    },
    {
      "superId": "a02",
      "id": "u04",
      "name": "Sara",
      "wallet": 250,
      "phone": "",
      "pix": ""
    },
    {
      "superId": "a01s01",
      "id": "u02",
      "name": "Sally",
      "wallet": 300,
      "phone": "",
      "pix": ""
    },
    {
      "superId": "a01s01",
      "id": "u02",
      "name": "Anderson",
      "wallet": 350,
      "phone": "",
      "pix": ""
    },
    {
      "superId": "a02s01",
      "id": "u02",
      "name": "Johny",
      "wallet": 400,
      "phone": "",
      "pix": ""
    },
    {
      "superId": "a02s01",
      "id": "u02",
      "name": "Maddie",
      "wallet": 450,
      "phone": "",
      "pix": ""
    }
  ],
  "bets": [
    {
      "id": "betId01",
      "userId": "u01",
      "numbers": [1, 7, 15, 22],
      "lottery": "Lotofácil",
      "sorteioNumber": "3043",
      "timestamp": "Sat Mar 02 2024 15:15:52 GMT+0000 (Horário do Meridiano de Greenwich)",
      "result": "pending"
    },
    {
      "id": "betId02",
      "userId": "u01",
      "numbers": [7, 12, 22, 25, 26, 28],
      "lottery": "Lotofácil",
      "sorteioNumber": "3043",
      "timestamp": "Sat Mar 02 2024 15:15:52 GMT+0000 (Horário do Meridiano de Greenwich)",
      "result": "pending"
    },
    {
      "id": "betId03",
      "userId": "u02",
      "numbers": [1, 2, 3, 4, 5],
      "lottery": "Lotofácil",
      "sorteioNumber": "3043",
      "timestamp": "Sat Mar 02 2024 15:15:52 GMT+0000 (Horário do Meridiano de Greenwich)",
      "result": "pending"
    }
  ],
  "modalidadesCaixa": [
    {
      "name": "Lotofácil",
      "color": "#930089"
    },
    {
      "name": "ERRE X",
      "color": "purple"
    },
    {
      "name": "Megasena",
      "color": "#209869"
    },
    {
      "name": "Lotomania",
      "color": "#F78100"
    },
    {
      "name": "Quina",
      "color": "#260085"
    },
    {
      "name": "Dupla Sena",
      "color": "#bf194e"
    },
    {
      "name": "Dia de Sorte",
      "color": "#CB852B"
    },
    {
      "name": "Timemania",
      "color": "#02FF02"
    },
    {
      "name": "+Milionária",
      "color": "#2E3078"
    },
    {
      "name": "Federal",
      "color": "#103099"
    },
    {
      "name": "Loteca",
      "color": "#fb1f00"
    },
    {
      "name": "Super Sete",
      "color": "#A8CF45"
    }
  ],
  "generalSettings": {
    "bilhetes_horarioLimiteApotas": "20:00:00",
    "bilhetes_valorMaximoPorBilhete": 20,
    "bilhetes_quantidadeMaximaDeBilhetesPorCliente": 20,
    "bilhetes_quantidadeMaximaDeBilhetesDuplicadosPorSorteio": 20,
    "bilhetes_quantidadeMaximaDeBilhetesDuplicadosPorAposta": 20,
    "bilhetes_bloquearCadastroDeBilhetesDuplicados": false,
    "surpresinha_permitirCadastroIlimitadoDeBilhetes": true,
    "surpresinha_permitirCadastroIlimitadoDeBilhetesDuplicados": false,
    "app_exibirAlertaDeApostasDuplicadasNaHoraDaCriacao": true,
    "app_iniciarFiltroDeApostasExibindoTodasAsApostas": true,
    "app_exibirTodosOsClientesParaTodosOsVendedores": false,
    "app_exibirListaDeGanhadoresParaOsVendedores": true,
    "app_exibirListaDeGanhadoresParaOsClientes": false,
    "app_exibirListaDeGanhadoresParaTodosOsUsuarios": false,
    "app_exibirVendedoresInativos": false,
    "permissoesAdm_ativarValidacaoDeQuantidadeMaxDeBilhetesParaOsAdmins": true,
    "permissoesAdm_ativarValidacaoDoValorMaxPorBilhetesParaOsAdmins": true,
    "permissoesAdm_ativarValidacaoDoBloqueioDeBilhetesDuplicadosParaOsAdmins": true,
    "permissoesAdm_ativarValidacaoDoHorarioDeBloqueioParaOsAdmins": true,
    "permissoesAdm_ativarValidacaoDoHorarioDeInicioDasVendasParaOsAdmins": true
  }
}
